more_termcolor/__init__.py
more_termcolor/colors.py
more_termcolor/convert.py
more_termcolor/core.py
more_termcolor/main.py
more_termcolor/util.py
more_termcolor-1.1.3.dist-info/LICENSE
more_termcolor-1.1.3.dist-info/METADATA
more_termcolor-1.1.3.dist-info/WHEEL
more_termcolor-1.1.3.dist-info/top_level.txt
more_termcolor-1.1.3.dist-info/RECORD
