Metadata-Version: 2.1
Name: more-termcolor
Version: 1.1.3
Summary: All colors, with support for nested colors, convenience methods and full original termcolor compatability.
Home-page: https://github.com/giladbarnea/more_termcolor
Author: Gilad Barnea
Author-email: giladbrn@gmail.com
License: MIT
Keywords: termcolor,color,colors,terminal,ansi,formatting
Platform: UNKNOWN
Classifier: Development Status :: 4 - Beta
Classifier: Environment :: Console
Classifier: Intended Audience :: Developers
Classifier: License :: OSI Approved :: MIT License
Classifier: Operating System :: OS Independent
Classifier: Programming Language :: Python :: 3 :: Only
Classifier: Topic :: Terminals
Requires-Python: >=3.7
Provides-Extra: dev
Requires-Dist: pytest ; extra == 'dev'
Requires-Dist: ipdb ; extra == 'dev'
Requires-Dist: IPython ; extra == 'dev'
Requires-Dist: semver ; extra == 'dev'
Requires-Dist: birdseye ; extra == 'dev'
